altair_morberg/__init__.py
altair_morberg/_nbdev.py
altair_morberg/core.py
altair_morberg-0.0.6.dist-info/LICENSE
altair_morberg-0.0.6.dist-info/METADATA
altair_morberg-0.0.6.dist-info/WHEEL
altair_morberg-0.0.6.dist-info/entry_points.txt
altair_morberg-0.0.6.dist-info/top_level.txt
altair_morberg-0.0.6.dist-info/RECORD
