Metadata-Version: 2.1
Name: altair-morberg
Version: 0.0.6
Summary: A personal theme for Altair
Home-page: https://github.com/morberg/altair_morberg/tree/master/
Author: Niklas Morberg
Author-email: niklas.morberg@gmail.com
License: Apache Software License 2.0
Keywords: altair theme
Platform: UNKNOWN
Classifier: Development Status :: 5 - Production/Stable
Classifier: Intended Audience :: Developers
Classifier: License :: OSI Approved :: Apache Software License
Classifier: Natural Language :: English
Classifier: Programming Language :: Python :: 3.6
Classifier: Programming Language :: Python :: 3.7
Classifier: Programming Language :: Python :: 3.8
Requires-Python: >=3.6
Requires-Dist: altair (>=4.0)
